vizman/.DS_Store
vizman/__init__.py
vizman/colors.json
vizman/fonts/.DS_Store
vizman/fonts/Atkinson-Bold.ttf
vizman/fonts/Atkinson-BoldItalic.ttf
vizman/fonts/Atkinson-Italic.ttf
vizman/fonts/Atkinson-Regular.ttf
vizman/fonts/IBMPlexMono-Bold.ttf
vizman/fonts/IBMPlexMono-BoldItalic.ttf
vizman/fonts/IBMPlexMono-ExtraLight.ttf
vizman/fonts/IBMPlexMono-ExtraLightItalic.ttf
vizman/fonts/IBMPlexMono-Italic.ttf
vizman/fonts/IBMPlexMono-Light.ttf
vizman/fonts/IBMPlexMono-LightItalic.ttf
vizman/fonts/IBMPlexMono-Medium.ttf
vizman/fonts/IBMPlexMono-MediumItalic.ttf
vizman/fonts/IBMPlexMono-Regular.ttf
vizman/fonts/IBMPlexMono-SemiBold.ttf
vizman/fonts/IBMPlexMono-SemiBoldItalic.ttf
vizman/fonts/IBMPlexMono-Thin.ttf
vizman/fonts/IBMPlexMono-ThinItalic.ttf
vizman/fonts/SpaceMono-Bold.ttf
vizman/fonts/SpaceMono-BoldItalic.ttf
vizman/fonts/SpaceMono-Italic.ttf
vizman/fonts/SpaceMono-Regular.ttf
vizman/sizes.json
vizman/viz.py
vizman-0.2.2.dist-info/METADATA
vizman-0.2.2.dist-info/WHEEL
vizman-0.2.2.dist-info/RECORD
